unide/__init__.py
unide/common.py
unide/measurement.py
unide/message.py
unide/process.py
unide/schema.py
unide/util.py
unide_python-0.2.0.dist-info/DESCRIPTION.rst
unide_python-0.2.0.dist-info/LICENSE.txt
unide_python-0.2.0.dist-info/METADATA
unide_python-0.2.0.dist-info/RECORD
unide_python-0.2.0.dist-info/WHEEL
unide_python-0.2.0.dist-info/metadata.json
unide_python-0.2.0.dist-info/top_level.txt
unide_python-0.2.0.dist-info/zip-safe
