Metadata-Version: 2.0
Name: unide-python
Version: 0.2.0
Summary: An API for PPMP, the Production Performance Management Protocol
Home-page: https://github.com/eclipse/unide.python
Author: Contact Software
Author-email: unide@contact-software.com
License: Eclipe Public License
Keywords: PPMP IoT Unide Eclipse
Platform: UNKNOWN
Classifier: Development Status :: 4 - Beta
Classifier: Intended Audience :: Developers
Classifier: License :: OSI Approved
Classifier: Natural Language :: English
Classifier: Operating System :: MacOS :: MacOS X
Classifier: Operating System :: Microsoft :: Windows
Classifier: Operating System :: POSIX
Classifier: Programming Language :: Python
Classifier: Programming Language :: Python :: 2
Classifier: Programming Language :: Python :: 2.7
Classifier: Programming Language :: Python :: 3
Classifier: Programming Language :: Python :: 3.4
Classifier: Programming Language :: Python :: 3.5
Classifier: Programming Language :: Python :: 3.6
Classifier: Topic :: Communications
Classifier: Topic :: Internet
Requires-Dist: python-dateutil
Requires-Dist: six
